yarik_django_airflow_api_manager/__init__.py
yarik_django_airflow_api_manager/airflow_api_manager.py
yarik_django_airflow_api_manager/airflow_api_manager.pyi
yarik_django_airflow_api_manager/apps.py
yarik_django_airflow_api_manager/py.typed
yarik_django_airflow_api_manager/urls.py
yarik_django_airflow_api_manager/utils.py
yarik_django_airflow_api_manager/view_handlers.py
yarik_django_airflow_api_manager/view_handlers.pyi
yarik_django_airflow_api_manager/views.py
yarik_django_airflow_api_manager/conf/__init__.py
yarik_django_airflow_api_manager/conf/settings.py
yarik_django_airflow_api_manager-2.0.20.dist-info/licenses/LICENSE
yarik_django_airflow_api_manager-2.0.20.dist-info/METADATA
yarik_django_airflow_api_manager-2.0.20.dist-info/WHEEL
yarik_django_airflow_api_manager-2.0.20.dist-info/top_level.txt
yarik_django_airflow_api_manager-2.0.20.dist-info/RECORD
