Metadata-Version: 2.4
Name: yarik-django-airflow-api-manager
Version: 2.0.20
Summary: Airflow api manager django app.
Author-email: YARIK <yarik@mail.ru>
Classifier: Environment :: Web Environment
Classifier: Framework :: Django
Classifier: Framework :: Django :: 5.2
Classifier: Intended Audience :: Developers
Classifier: License :: OSI Approved :: BSD License
Classifier: Operating System :: OS Independent
Classifier: Programming Language :: Python
Classifier: Programming Language :: Python :: 3
Classifier: Programming Language :: Python :: 3 :: Only
Classifier: Programming Language :: Python :: 3.10
Classifier: Programming Language :: Python :: 3.11
Classifier: Programming Language :: Python :: 3.12
Classifier: Programming Language :: Python :: 3.13
Classifier: Topic :: Internet :: WWW/HTTP
Classifier: Topic :: Internet :: WWW/HTTP :: Dynamic Content
Requires-Python: >=3.12
License-File: LICENSE
Requires-Dist: asgiref<=3.10.0
Requires-Dist: Django<=5.2.8
Requires-Dist: greenlet<=3.2.4
Requires-Dist: psycopg2-binary<=2.9.11
Requires-Dist: pydantic<=2.12.4
Requires-Dist: pydantic_core<=2.41.5
Requires-Dist: pyparsing<=3.2.5
Requires-Dist: six<=1.17.0
Requires-Dist: SQLAlchemy<=2.0.44
Requires-Dist: sqlparse<=0.5.3
Requires-Dist: typing_extensions<=4.15.0
Requires-Dist: requests<=2.32.5
Requires-Dist: PyJWT<=2.10.1
Requires-Dist: cryptography<=46.0.3
Dynamic: license-file
